wagtail_shop/__init__.py
wagtail_shop/abstract_models.py
wagtail_shop/admin.py
wagtail_shop/apps.py
wagtail_shop/disabled_models.py
wagtail_shop/models.py
wagtail_shop/product_admin.py
wagtail_shop/signals.py
wagtail_shop/tests.py
wagtail_shop/views.py
wagtail_shop/wagtail_hooks.py
wagtail_shop/core/__init__.py
wagtail_shop/core/customisation.py
wagtail_shop/management/__init__.py
wagtail_shop/management/commands/__init__.py
wagtail_shop/management/commands/wagtail_shop_fork_app.py
wagtail_shop/migrations/0001_initial.py
wagtail_shop/migrations/0002_auto_20181130_1102.py
wagtail_shop/migrations/__init__.py
wagtail_shop/oscar_apps/__init__.py
wagtail_shop/oscar_apps/catalogue/__init__.py
wagtail_shop/oscar_apps/catalogue/abstract_models.py
wagtail_shop/oscar_apps/catalogue/admin.py
wagtail_shop/oscar_apps/catalogue/config.py
wagtail_shop/oscar_apps/catalogue/forms.py
wagtail_shop/oscar_apps/catalogue/models.py
wagtail_shop/oscar_apps/catalogue/migrations/0001_initial.py
wagtail_shop/oscar_apps/catalogue/migrations/0002_auto_20150217_1221.py
wagtail_shop/oscar_apps/catalogue/migrations/0003_data_migration_slugs.py
wagtail_shop/oscar_apps/catalogue/migrations/0004_auto_20150217_1710.py
wagtail_shop/oscar_apps/catalogue/migrations/0005_auto_20150604_1450.py
wagtail_shop/oscar_apps/catalogue/migrations/0006_auto_20150807_1725.py
wagtail_shop/oscar_apps/catalogue/migrations/0007_auto_20151207_1440.py
wagtail_shop/oscar_apps/catalogue/migrations/0008_auto_20160304_1652.py
wagtail_shop/oscar_apps/catalogue/migrations/0009_slugfield_noop.py
wagtail_shop/oscar_apps/catalogue/migrations/0010_auto_20170420_0439.py
wagtail_shop/oscar_apps/catalogue/migrations/0011_auto_20170422_1355.py
wagtail_shop/oscar_apps/catalogue/migrations/0012_auto_20170609_1902.py
wagtail_shop/oscar_apps/catalogue/migrations/0013_auto_20170821_1548.py
wagtail_shop/oscar_apps/catalogue/migrations/0014_auto_20181205_1631.py
wagtail_shop/oscar_apps/catalogue/migrations/0015_auto_20181205_1640.py
wagtail_shop-0.1.0b2.dist-info/LICENSE
wagtail_shop-0.1.0b2.dist-info/METADATA
wagtail_shop-0.1.0b2.dist-info/WHEEL
wagtail_shop-0.1.0b2.dist-info/top_level.txt
wagtail_shop-0.1.0b2.dist-info/RECORD
