Metadata-Version: 2.1
Name: wagtail-shop
Version: 0.1.0b2
Summary: Shop for Wagtail
Home-page: https://github.com/ladrua/wagtail-shop
Author: Stian Aurdal
Author-email: stian@aurdal.io
License: BSD License
Platform: UNKNOWN
Classifier: Environment :: Web Environment
Classifier: Framework :: Django
Classifier: Framework :: Django :: 2.1
Classifier: Intended Audience :: Developers
Classifier: License :: OSI Approved :: BSD License
Classifier: Operating System :: OS Independent
Classifier: Programming Language :: Python
Classifier: Programming Language :: Python :: 3.5
Classifier: Programming Language :: Python :: 3.6
Classifier: Topic :: Internet :: WWW/HTTP
Classifier: Topic :: Internet :: WWW/HTTP :: Dynamic Content
Requires-Dist: wagtail
Requires-Dist: django-oscar
